[
  {
    "Ticker":"LYP6.DE",
    "ETF naam":"Amundi Core Stoxx Europe 600 UCITS ETF Acc",
    "Huidige waarde":"€278.25",
    "Verschil tot piek (12m)":"€-27.55 (-9.01%)",
    "Stijging (4m)":"nan%",
    "Stijging (12m)":"nan%",
    "Stijging (5y)":"nan%"
  },
  {
    "Ticker":"IBC3.DE",
    "ETF naam":"iShares Core MSCI EM IMI UCITS ETF",
    "Huidige waarde":"€5.35",
    "Verschil tot piek (12m)":"€-0.59 (-9.96%)",
    "Stijging (4m)":"nan%",
    "Stijging (12m)":"nan%",
    "Stijging (5y)":"nan%"
  },
  {
    "Ticker":"ESIT.DE",
    "ETF naam":"iShares MSCI Europe Information Technology Sector UCITS ETF",
    "Huidige waarde":"€8.79",
    "Verschil tot piek (12m)":"€-0.76 (-8.00%)",
    "Stijging (4m)":"nan%",
    "Stijging (12m)":"nan%",
    "Stijging (5y)":"nan%"
  },
  {
    "Ticker":"EX25.VI",
    "ETF naam":"iShares STOXX Europe 600 UCITS ETF (DE)",
    "Huidige waarde":"€57.14",
    "Verschil tot piek (12m)":"€-5.85 (-9.29%)",
    "Stijging (4m)":"2.22%",
    "Stijging (12m)":"5.09%",
    "Stijging (5y)":"36.47%"
  },
  {
    "Ticker":"VWCE.DE",
    "ETF naam":"Vanguard FTSE All-World UCITS ETF USD Accumulation",
    "Huidige waarde":"€142.98",
    "Verschil tot piek (12m)":"€-7.88 (-5.22%)",
    "Stijging (4m)":"nan%",
    "Stijging (12m)":"nan%",
    "Stijging (5y)":"nan%"
  },
  {
    "Ticker":"IS3R.DE",
    "ETF naam":"iShares Edge MSCI World Momentum Factor UCITS ETF",
    "Huidige waarde":"€81.05",
    "Verschil tot piek (12m)":"€-6.22 (-7.13%)",
    "Stijging (4m)":"nan%",
    "Stijging (12m)":"nan%",
    "Stijging (5y)":"nan%"
  },
  {
    "Ticker":"SXR8.DE",
    "ETF naam":"iShares Core S&P 500 UCITS ETF USD (Acc)",
    "Huidige waarde":"€608.96",
    "Verschil tot piek (12m)":"€-34.86 (-5.41%)",
    "Stijging (4m)":"nan%",
    "Stijging (12m)":"nan%",
    "Stijging (5y)":"nan%"
  },
  {
    "Ticker":"VUSA.AS",
    "ETF naam":"Vanguard S&P 500 UCITS ETF",
    "Huidige waarde":"€107.43",
    "Verschil tot piek (12m)":"€-6.41 (-5.63%)",
    "Stijging (4m)":"nan%",
    "Stijging (12m)":"nan%",
    "Stijging (5y)":"nan%"
  },
  {
    "Ticker":"EUNK.DE",
    "ETF naam":"iShares Core MSCI Europe UCITS ETF EUR (Acc)",
    "Huidige waarde":"€91.49",
    "Verschil tot piek (12m)":"€-9.23 (-9.16%)",
    "Stijging (4m)":"nan%",
    "Stijging (12m)":"nan%",
    "Stijging (5y)":"nan%"
  },
  {
    "Ticker":"CEMR.DE",
    "ETF naam":"iShares Edge MSCI Europe Momentum Factor UCITS ETF EUR (Acc)",
    "Huidige waarde":"€14.11",
    "Verschil tot piek (12m)":"€-1.72 (-10.86%)",
    "Stijging (4m)":"nan%",
    "Stijging (12m)":"nan%",
    "Stijging (5y)":"nan%"
  },
  {
    "Ticker":"EQAC.MI",
    "ETF naam":"Invesco EQQQ NASDAQ-100 UCITS ETF Acc",
    "Huidige waarde":"€356.72",
    "Verschil tot piek (12m)":"€-27.46 (-7.15%)",
    "Stijging (4m)":"nan%",
    "Stijging (12m)":"nan%",
    "Stijging (5y)":"nan%"
  }
]